MANIFEST.in
README.rst
setup.cfg
setup.py
netbox_portmanager/__init__.py
netbox_portmanager/admin.py
netbox_portmanager/filtersets.py
netbox_portmanager/forms.py
netbox_portmanager/models.py
netbox_portmanager/navigation.py
netbox_portmanager/tables.py
netbox_portmanager/template_code.py
netbox_portmanager/urls.py
netbox_portmanager/utils.py
netbox_portmanager/views.py
netbox_portmanager.egg-info/PKG-INFO
netbox_portmanager.egg-info/SOURCES.txt
netbox_portmanager.egg-info/dependency_links.txt
netbox_portmanager.egg-info/not-zip-safe
netbox_portmanager.egg-info/requires.txt
netbox_portmanager.egg-info/top_level.txt
netbox_portmanager/api/__init__.py
netbox_portmanager/api/serializers.py
netbox_portmanager/api/urls.py
netbox_portmanager/api/views.py
netbox_portmanager/migrations/0001_initial.py
netbox_portmanager/migrations/__init__.py
netbox_portmanager/static/netbox_portmanager/img/connected.png
netbox_portmanager/static/netbox_portmanager/img/disabled.png
netbox_portmanager/static/netbox_portmanager/img/notconnected.png
netbox_portmanager/switches/__init__.py
netbox_portmanager/switches/cisco_switch.py
netbox_portmanager/switches/general_switch.py
netbox_portmanager/switches/interface.py
netbox_portmanager/switches/utils.py
netbox_portmanager/switches/vlan.py
netbox_portmanager/templates/netbox_portmanager/device.html
netbox_portmanager/templates/netbox_portmanager/device_object.html
netbox_portmanager/templates/netbox_portmanager/devicegroup.html
netbox_portmanager/templates/netbox_portmanager/mac.html
netbox_portmanager/templates/netbox_portmanager/changelog/changelog.html
netbox_portmanager/templates/netbox_portmanager/generic/object.html
netbox_portmanager/templates/netbox_portmanager/htmx/table.html
netbox_portmanager/templates/netbox_portmanager/inc/paginator_htmx.html
netbox_portmanager/templates/netbox_portmanager/inc/table_htmx.html
netbox_portmanager/templatetags/portmanager_filters.py