Metadata-Version: 2.1
Name: netbox-portmanager
Version: 0.2.1
Summary: Netbox Plugin - Portmanager
Home-page: https://github.com/dansheps/netbox-secretstore/
Author: Michal Drobny
Author-email: ddrobny@ics.muni.cz
License: Apache 2.0
Download-URL: https://www.pypi.org/project/netbox-secretstore/
Platform: UNKNOWN
Requires-Python: >=3.8
